## 字典和集合

### 集合
#### **{'a'}**性能优越于**set(['a'])**的理由

```
>>> def foo():
...   a = {'a'}
...   b = set(['a'])
...
>>> dis.dis(foo)
  2           0 LOAD_CONST               1 ('a')
              3 BUILD_SET                1
              6 STORE_FAST               0 (a)

  3           9 LOAD_GLOBAL              0 (set)
             12 LOAD_CONST               1 ('a')
             15 BUILD_LIST               1
             18 CALL_FUNCTION            1
             21 STORE_FAST               1 (b)
             24 LOAD_CONST               0 (None)
             27 RETURN_VALUE
```

#### 空set
set()

